{
  "templateName": "Test Template",
  "sections": [
    {
      "icon": "section1_icon",
      "label_ar": "القسم 1",
      "label_fr": "Section 1",
      "label_en": "Section 1",
      "desc_ar": "وصف القسم 1",
      "desc_fr": "Description of section 1",
      "desc_en": "Description of section 1",
      "variables": [
        {
          "name": "var1",
          "required": true,
          "type": "text",
          "icon": "var1_icon",
          "min": 1,
          "max": 10,
          "prefix": "prefix1",
          "suffix": "suffix1",
          "default": "default1",
          "label_ar": "المتغير 1",
          "label_fr": "Variable 1",
          "label_en": "Variable 1",
          "desc_ar": "وصف المتغير 1",
          "desc_fr": "Description of variable 1",
          "desc_en": "Description of variable 1"
        },
        {
          "name": "var2",
          "required": false,
          "type": "counter",
          "icon": "var2_icon",
          "min": 0,
          "max": 100,
          "prefix": "prefix2",
          "suffix": "suffix2",
          "default": "default2",
          "label_ar": "المتغير 2",
          "label_fr": "Variable 2",
          "label_en": "Variable 2",
          "desc_ar": "وصف المتغير 2",
          "desc_fr": "Description of variable 2",
          "desc_en": "Description of variable 2"
        }
      ]
    },
    {
      "icon": "section2_icon",
      "label_ar": "القسم 2",
      "label_fr": "Section 2",
      "label_en": "Section 2",
      "desc_ar": "وصف القسم 2",
      "desc_fr": "Description of section 2",
      "desc_en": "Description of section 2",
      "variables": [
        {
          "name": "main_font_name",
          "required": false,
          "type": "font",
          "icon": "var3_icon",
          "min": 1,
          "max": 1,
          "prefix": "",
          "suffix": "",
          "default": "Noto Naskh Arabic",
          "label_ar": "الخط",
          "label_fr": "Police",
          "label_en": "font",
          "desc_ar": "",
          "desc_fr": "",
          "desc_en": ""
        },
        {
          "name": "page_color",
          "required": false,
          "type": "text",
          "icon": "var3_icon",
          "min": 1,
          "max": 10,
          "prefix": "",
          "suffix": "",
          "default": "white",
          "label_ar": "لون الصفحة",
          "label_fr": "color",
          "label_en": "color",
          "desc_ar": "",
          "desc_fr": "",
          "desc_en": ""
        },
        {
          "name": "page_width",
          "required": false,
          "type": "counter",
          "icon": "var3_icon",
          "min": 1,
          "max": 5000,
          "prefix": "",
          "suffix": "pt",
          "default": "595",
          "label_ar": "عرض الصفحة",
          "label_fr": "width",
          "label_en": "width",
          "desc_ar": "",
          "desc_fr": "",
          "desc_en": ""
        }
      ]
    }
  ],
  "records": [
    {
      "name": "Record1",
      "icon": "icon1.png",
      "label_ar": "السجل 1",
      "label_fr": "Record 1",
      "label_en": "Record 1",
      "desc_ar": "Description AR 1",
      "desc_fr": "Description FR 1",
      "desc_en": "Description EN 1",
      "variables": [
        {
          "name": "Var1",
          "required": true,
          "type": "text",
          "icon": "icon1.png",
          "min": 0,
          "max": 10,
          "prefix": "",
          "suffix": "",
          "default": "",
          "label_ar": "Var1 Label AR",
          "label_fr": "Var1 Label FR",
          "label_en": "Var1 Label EN",
          "desc_ar": "Var1 Description AR",
          "desc_fr": "Var1 Description FR",
          "desc_en": "Var1 Description EN"
        },
        {
          "name": "Var2",
          "required": false,
          "type": "number",
          "icon": "icon2.png",
          "min": 0,
          "max": 100,
          "prefix": "$",
          "suffix": "",
          "default": "",
          "label_ar": "Var2 Label AR",
          "label_fr": "Var2 Label FR",
          "label_en": "Var2 Label EN",
          "desc_ar": "Var2 Description AR",
          "desc_fr": "Var2 Description FR",
          "desc_en": "Var2 Description EN"
        }
      ]
    },
    {
      "name": "Record2",
      "icon": "icon2.png",
      "label_ar": "السجل 2",
      "label_fr": "Record 2",
      "label_en": "Record 2",
      "desc_ar": "Description AR 2",
      "desc_fr": "Description FR 2",
      "desc_en": "Description EN 2",
      "variables": [
        {
          "name": "Var3",
          "required": true,
          "type": "switch",
          "icon": "icon3.png",
          "min": 0,
          "max": 1,
          "prefix": "",
          "suffix": "",
          "default": "true",
          "label_ar": "Var3 Label AR",
          "label_fr": "Var3 Label FR",
          "label_en": "Var3 Label EN",
          "desc_ar": "Var3 Description AR",
          "desc_fr": "Var3 Description FR",
          "desc_en": "Var3 Description EN"
        },
        {
          "name": "Var4",
          "required": false,
          "type": "text",
          "icon": "icon4.png",
          "min": 0,
          "max": 50,
          "prefix": "",
          "suffix": "",
          "default": "",
          "label_ar": "Var4 Label AR",
          "label_fr": "Var4 Label FR",
          "label_en": "Var4 Label EN",
          "desc_ar": "Var4 Description AR",
          "desc_fr": "Var4 Description FR",
          "desc_en": "Var4 Description EN"
        }
      ]
    }
  ]
}